odoo/addons/shift/README.rst
odoo/addons/shift/__init__.py
odoo/addons/shift/__manifest__.py
odoo/addons/shift/post_init.py
odoo/addons/shift/rename_beesdoo.py
odoo/addons/shift/data/cron.xml
odoo/addons/shift/data/mail_template.xml
odoo/addons/shift/data/system_parameter.xml
odoo/addons/shift/demo/exempt_reason.xml
odoo/addons/shift/demo/templates.xml
odoo/addons/shift/demo/workers.xml
odoo/addons/shift/i18n/en_US.po
odoo/addons/shift/i18n/fr.po
odoo/addons/shift/i18n/nl.po
odoo/addons/shift/i18n/shift.pot
odoo/addons/shift/models/__init__.py
odoo/addons/shift/models/cooperative_status.py
odoo/addons/shift/models/planning.py
odoo/addons/shift/models/res_config_settings.py
odoo/addons/shift/models/res_partner.py
odoo/addons/shift/models/shift_shift.py
odoo/addons/shift/readme/CONFIGURE.rst
odoo/addons/shift/readme/CONTRIBUTORS.rst
odoo/addons/shift/readme/DESCRIPTION.rst
odoo/addons/shift/readme/HISTORY.rst
odoo/addons/shift/security/group.xml
odoo/addons/shift/security/ir.model.access.csv
odoo/addons/shift/static/description/icon.png
odoo/addons/shift/tests/__init__.py
odoo/addons/shift/tests/test_shift.py
odoo/addons/shift/views/cooperative_status.xml
odoo/addons/shift/views/exempt_reason.xml
odoo/addons/shift/views/menu.xml
odoo/addons/shift/views/planning.xml
odoo/addons/shift/views/res_config_settings_view.xml
odoo/addons/shift/views/task.xml
odoo/addons/shift/views/task_template.xml
odoo/addons/shift/wizard/__init__.py
odoo/addons/shift/wizard/assign_super_coop.py
odoo/addons/shift/wizard/assign_super_coop.xml
odoo/addons/shift/wizard/batch_template.py
odoo/addons/shift/wizard/batch_template.xml
odoo/addons/shift/wizard/extension.py
odoo/addons/shift/wizard/extension.xml
odoo/addons/shift/wizard/holiday.py
odoo/addons/shift/wizard/holiday.xml
odoo/addons/shift/wizard/instantiate_planning.py
odoo/addons/shift/wizard/instantiate_planning.xml
odoo/addons/shift/wizard/subscribe.py
odoo/addons/shift/wizard/subscribe.xml
odoo12_addon_shift-12.0.5.0.0.99.dev2.dist-info/METADATA
odoo12_addon_shift-12.0.5.0.0.99.dev2.dist-info/WHEEL
odoo12_addon_shift-12.0.5.0.0.99.dev2.dist-info/top_level.txt
odoo12_addon_shift-12.0.5.0.0.99.dev2.dist-info/RECORD
